bayesianlogic/__init__.py
bayesianlogic-0.0.1a1.dist-info/LICENSE
bayesianlogic-0.0.1a1.dist-info/METADATA
bayesianlogic-0.0.1a1.dist-info/WHEEL
bayesianlogic-0.0.1a1.dist-info/top_level.txt
bayesianlogic-0.0.1a1.dist-info/RECORD
