Metadata-Version: 2.1
Name: bayesianlogic
Version: 0.0.1a1
Summary: A package for Bayesian Inference
Home-page: https://github.com/Bayesian-Logic/bayesianlogic
Author: Nimar Arora
Author-email: nimar.arora@gmail.com
License: UNKNOWN
Platform: UNKNOWN
Classifier: Development Status :: 1 - Planning
Classifier: Intended Audience :: Science/Research
Classifier: Programming Language :: Python :: 3
Classifier: License :: OSI Approved :: MIT License
Classifier: Operating System :: OS Independent
Classifier: Topic :: Scientific/Engineering :: Artificial Intelligence
Requires-Python: >=3.6
